{
  "project_info": {
    "project_number": "427199057524",
    "project_id": "housweet-dfb9d",
    "storage_bucket": "housweet-dfb9d.firebasestorage.app"
  },
  "client": [
    {
      "client_info": {
        "mobilesdk_app_id": "1:427199057524:android:b27fa7553848e16ccd4b21",
        "android_client_info": {
          "package_name": "com.housweet.app"
        }
      },
      "oauth_client": [],
      "api_key": [
        {
          "current_key": "AIzaSyAHgIqvkKcdh_5xdJ6JdB9x4-kRyxaZwFI"
        }
      ],
      "services": {
        "appinvite_service": {
          "other_platform_oauth_client": []
        }
      }
    }
  ],
  "configuration_version": "1"
}